aes_result_buffer/rtl/aes_result_buffer.v
`timescale 1ns/1ps
module aes_result_buffer(
    // inputs
    input logic clk,
    input logic reset,
    input logic zeroize,
    input logic [127:0] result_in,
    input logic result_valid,
    input logic rd_en,
    input logic [1:0] rd_addr,
    // outputs
    output logic [31:0] rd_data,
    output logic rd_valid,
    output logic result_ready
);

    // read words (big end)
    logic [31:0] r0,r1,r2,r3;


    // sequential logic -> capture result / clear state
    always_ff @(posedge clk) begin
        if (reset || zeroize) begin
            r0 <= '0;
            r1 <= '0;
            r2 <= '0;
            r3 <= '0;            
            result_ready <= 1'b0;
        end
        else begin
            if (result_valid) begin
                r0 <= result_in[127:96];
                r1 <= result_in[95:64];
                r2 <= result_in[63:32];
                r3 <= result_in[31:0];
                result_ready <= 1'b1;  
            end
        end
    end

    // read mux (comb logic)
    always_comb begin
        rd_data = 32'h0000_0000;
        if (rd_en && result_ready) begin
            case (rd_addr)                
                2'd0: rd_data = r0;
                2'd1: rd_data = r1;
                2'd2: rd_data = r2;
                2'd3: rd_data = r3;
                default: rd_data = 32'h0000_0000;
            endcase
        end
    end

    assign rd_valid = rd_en && result_ready;

endmodule

aes_result_buffer/sim/tb_aes_result_buffer.sv
`timescale 1ns/1ps
module tb_aes_result_buffer;
    // DUT inputs
    logic clk;
    logic reset;
    logic zeroize;
    logic [127:0] result_in;
    logic result_valid;
    logic rd_en;
    logic [1:0] rd_addr;

    // DUT outputs
    logic [31:0] rd_data;
    logic rd_valid;
    logic result_ready;
    
    // DUT
    aes_result_buffer dut (
        .clk(clk),
        .reset(reset),
        .zeroize(zeroize),
        .result_in(result_in),
        .result_valid(result_valid),
        .rd_en(rd_en),
        .rd_addr(rd_addr),
        .rd_data(rd_data),
        .rd_valid(rd_valid),
        .result_ready(result_ready)
    );

    initial begin
        clk = 1'b0;
        forever #5 clk = ~clk;
    end

    task automatic tb_expect_bit(string name, logic actual, logic expected);
        if (actual !== expected) begin
            $display("FAIL: %s at t=%0t actual=%b expected=%b", name, $time, actual, expected);
            $finish;
        end
        else begin
            $display("PASS: %s at t=%0t", name, $time);
        end
    endtask

    task automatic tb_expect_32(string name, logic [31:0] actual, logic [31:0] expected);
        if (actual !== expected) begin
            $display("FAIL: %s at t=%0t actual=%h expected=%h",name, $time, actual, expected);
            $finish;
        end
        else begin
            $display("PASS: %s at t=%0t", name, $time);
        end
    endtask

    task automatic tb_expect_mask(string name, logic [3:0] actual, logic [3:0] expected);
        if (actual !== expected) begin
            $display("FAIL: %s at t=%0t actual=%b expected=%b", name, $time, actual, expected);
            $finish;
        end
        else begin
            $display("PASS: %s at t=%0t", name, $time);
        end
    endtask

    task automatic do_reset();
        begin
            @(negedge clk);
            reset = 1'b1; 
            zeroize = 1'b0;
            result_valid = 1'b0;
            rd_en = 1'b0;
            @(negedge clk);
            @(negedge clk);
            reset = 1'b0;
            @(posedge clk); #1;
        end
    endtask

    initial begin
        $display("=== aes_result_buffer TB ===");
        // initial conds
        reset = 1'b0;
        zeroize = 1'b0;
        result_in = 128'h0;
        result_valid = 1'b0;
        rd_en = 1'b0;
        rd_addr = 2'd0;
        
        // dumps
        $dumpfile("tb_aes_result_buffer.vcd");
        $dumpvars(0, tb_aes_result_buffer);
        
        // Test 1: reset
        $display("Test 1: Reset");
        do_reset();
        tb_expect_bit("reset: result_ready=0", result_ready, 1'b0);
        tb_expect_bit("reset: rd_valid=0", rd_valid, 1'b0);
        tb_expect_32("reset: rd_data=0", rd_data, 32'h0000_0000);
        $display("Test 1: Pass");

        // Test 2: capture result
        $display("Test 2: Capture Result");
        @(negedge clk);
        result_in = 128'h00112233_44556677_8899AABB_CCDDEEFF;
        result_valid = 1'b1;
        @(posedge clk); #1;
        tb_expect_bit("capture result: result_valid=1", result_valid, 1'b1);
        tb_expect_bit("capture result: rd_valid=0 -> rd_en still 0", rd_valid, 1'b0);
        @(negedge clk);
        result_valid = 1'b0;
        $display("Test 2 Complete");                

        $display("Test 3: Test Read Mux");
        @(negedge clk);
        rd_en = 1'b1;
        rd_addr = 2'd0;
        @(posedge clk); #1;
        tb_expect_bit("Read mux: rd_valid=1", rd_valid, 1'b1);
        tb_expect_32("Read mux: rd_data = (r0=00112233)", rd_data,32'h00112233);

        @(negedge clk);
        rd_addr = 2'd1;
        @(posedge clk);
        tb_expect_bit("Read mux: rd_valid=1", rd_valid, 1'b1);
        tb_expect_32("Read mux: rd_data = (r1=44556677)", rd_data,32'h44556677);
        
        @(negedge clk); rd_addr = 2'd2; @(posedge clk); 
        tb_expect_bit("Read mux: rd_valid=1", rd_valid, 1'b1); 
        tb_expect_32("Read mux: rd_data = (r2=8899AABB)", rd_data, 32'h8899AABB);

        @(negedge clk); 
        rd_addr = 2'd3; 
        @(posedge clk);
        tb_expect_bit("Read mux: rd_valid=1", rd_valid, 1'b1); 
        tb_expect_32("Read mux: rd_data = (r3=CCDDEEFF)", rd_data, 32'hCCDDEEFF);

        $display("Test 3: Complete");
        // Test 4: zeroize clears stored result
        $display("Test 4: Zeroize clears result buffer");

        // capture result again
        do_reset();

        @(negedge clk);
        result_in = 128'h00112233_44556677_8899AABB_CCDDEEFF;
        result_valid = 1'b1;

        @(posedge clk); #1;
        tb_expect_bit("zeroize-pre: result_ready=1", result_ready, 1'b1);

        @(negedge clk);
        result_valid = 1'b0;
        zeroize = 1'b1;

        @(posedge clk); #1;
        tb_expect_bit("zeroize: result_ready=0", result_ready, 1'b0);
        tb_expect_bit("zeroize: rd_valid=0", rd_valid, 1'b0);
        tb_expect_32("zeroize: rd_data=0", rd_data, 32'h0000_0000);
        
        rd_addr = 2'd0;
        @(negedge clk);
        tb_expect_32("zeroize: r0 rd_data=0", rd_data, 32'h0000_0000);

        rd_addr = 2'd1;
        @(negedge clk);
        tb_expect_32("zeroize: r1 rd_data=0", rd_data, 32'h0000_0000);

        rd_addr = 2'd2;        
        @(negedge clk);        
        tb_expect_32("zeroize: r2 rd_data=0", rd_data, 32'h0000_0000);
        
        rd_addr = 2'd3;
        @(negedge clk);
        tb_expect_32("zeroize: r3 rd_data=0", rd_data, 32'h0000_0000);

        @(negedge clk);
        zeroize = 1'b0;

        $display("Test 4: Pass");

        $display("=== All Tests Complete ==="); $finish;
    end   

endmodule

aes_result_buffer/build/tb_aes_result_buffer.vcd
$date
	Fri Mar 20 12:24:59 2026
$end

$version
	Synopsys VCS version W-2024.09_Full64
$end

$timescale
	1ps
$end

$comment Csum: 1 c9a639e3e2eca394 $end


$scope module tb_aes_result_buffer $end
$var reg 1 ! clk $end
$var reg 1 " reset $end
$var reg 1 # zeroize $end
$var reg 128 $ result_in [127:0] $end
$var reg 1 % result_valid $end
$var reg 1 & rd_en $end
$var reg 2 ' rd_addr [1:0] $end
$var reg 32 ( rd_data [31:0] $end
$var reg 1 ) rd_valid $end
$var reg 1 * result_ready $end

$scope module dut $end
$var reg 1 ! clk $end
$var reg 1 " reset $end
$var reg 1 # zeroize $end
$var reg 128 $ result_in [127:0] $end
$var reg 1 % result_valid $end
$var reg 1 & rd_en $end
$var reg 2 ' rd_addr [1:0] $end
$var reg 32 ( rd_data [31:0] $end
$var reg 1 ) rd_valid $end
$var reg 1 * result_ready $end
$var reg 32 + r0 [31:0] $end
$var reg 32 , r1 [31:0] $end
$var reg 32 - r2 [31:0] $end
$var reg 32 . r3 [31:0] $end
$upscope $end

$upscope $end

$enddefinitions $end

#0
$dumpvars
0!
0&
0)
0"
x*
0%
0#
b00 '
b00000000000000000000000000000000 (
b00000000000000000000000000000000000000000000000000000000000000000000000000000000000000000000000000000000000000000000000000000000 $
bxxxxxxxxxxxxxxxxxxxxxxxxxxxxxxxx +
bxxxxxxxxxxxxxxxxxxxxxxxxxxxxxxxx ,
bxxxxxxxxxxxxxxxxxxxxxxxxxxxxxxxx -
bxxxxxxxxxxxxxxxxxxxxxxxxxxxxxxxx .
$end
#5000
1!
#10000
0!
1"
#15000
1!
0*
b00000000000000000000000000000000 +
b00000000000000000000000000000000 ,
b00000000000000000000000000000000 -
b00000000000000000000000000000000 .
#20000
0!
#25000
1!
#30000
0!
0"
#35000
1!
#40000
0!
b00000000000100010010001000110011010001000101010101100110011101111000100010011001101010101011101111001100110111011110111011111111 $
1%
#45000
1!
1*
b00000000000100010010001000110011 +
b01000100010101010110011001110111 ,
b10001000100110011010101010111011 -
b11001100110111011110111011111111 .
#50000
0!
0%
#55000
1!
#60000
0!
1&
1)
b00000000000100010010001000110011 (
#65000
1!
#70000
0!
b01 '
b01000100010101010110011001110111 (
#75000
1!
#80000
0!
b10 '
b10001000100110011010101010111011 (
#85000
1!
#90000
0!
b11 '
b11001100110111011110111011111111 (
#95000
1!
#100000
0!
1"
0&
0)
b00000000000000000000000000000000 (
#105000
1!
0*
b00000000000000000000000000000000 +
b00000000000000000000000000000000 ,
b00000000000000000000000000000000 -
b00000000000000000000000000000000 .
#110000
0!
#115000
1!
#120000
0!
0"
#125000
1!
#130000
0!
1%
#135000
1!
1*
b00000000000100010010001000110011 +
b01000100010101010110011001110111 ,
b10001000100110011010101010111011 -
b11001100110111011110111011111111 .
#140000
0!
0%
1#
#145000
1!
0*
b00000000000000000000000000000000 +
b00000000000000000000000000000000 ,
b00000000000000000000000000000000 -
b00000000000000000000000000000000 .
#146000
b00 '
#150000
0!
b01 '
#155000
1!
#160000
0!
b10 '
#165000
1!
#170000
0!
b11 '
#175000
1!
#180000
0!
#185000
1!
#190000
0!
0#
