key_vault_rom/rtl/key_vault_rom.v
/*
128 bit Key Vault with 32 bit reads
- Always diven outputs (low when disabled)
- Latched Tamper
- Read-once lockout
*/
`timescale 1ns/1ps
module key_vault_rom(
    input wire clk,
    input wire rst_n,
    input wire chip_en, // vault enable
    input wire read_en, // read enable
    input wire zeroize, // force vault low if we suspect tamper
    input wire [1:0] word_idx, // selects 1 of 4 keywords
    output reg [31:0] data_out, // always diven
    output wire      oe, // output enable
    output reg tamper_latched,
    output reg read_once_latched
);

    
    // For now hard coded AES key -> big endian
    localparam [31:0] KEY_W0 = 32'h00112233;
    localparam [31:0] KEY_W1 = 32'h44556677;
    localparam [31:0] KEY_W2 = 32'h8899AABB;
    localparam [31:0] KEY_W3 = 32'hCCDDEEFF;
    
    // read counter and edge dect
    reg [1:0] read_count;
    reg oe_d; // delayed oe
    reg lock_pending;
    wire read_pulse;

    assign oe = chip_en && read_en && !tamper_latched && !read_once_latched; // OE defn
    assign read_pulse = oe & ~oe_d; 

    // tamper and read-once latch -> added read counter
    always @(posedge clk or negedge rst_n) begin
        if (!rst_n) begin
            tamper_latched <= 1'b0;
            read_once_latched <= 1'b0;
            read_count <= 2'd0;
            oe_d <= 1'b0;
            lock_pending <= 1'b0;
        end
        else begin
            // edge dection via delayed oe
            oe_d <= oe;
            if (lock_pending && (oe_d == 1'b1) && (oe == 1'b0)) begin
                read_once_latched <= 1'b1;
                lock_pending      <= 1'b0;
            end
            // tamper lock
            if (zeroize) begin
                tamper_latched <= 1'b1;
                read_once_latched <= 1'b1; // close read latch 
                lock_pending <= 1'b0;
            end
            // count successful reads
            if (read_pulse) begin
                if (read_count != 2'd3) begin 
                    read_count <= read_count + 2'd1;
                end
                else begin
                    lock_pending <= 1'b1;
                end    
            end
            if ((read_count == 2'd3) && (oe_d == 1'b1) && (oe == 1'b0) && (read_pulse == 1'b0)) begin
                $display("im really bored");
            end
        end
    end


    always @* begin
        data_out = 32'h0000_0000;
        if (oe) begin
            case(word_idx)
                2'd0 : data_out = KEY_W0;
                2'd1 : data_out = KEY_W1;
                2'd2 : data_out = KEY_W2;
                2'd3 : data_out = KEY_W3;
                default : data_out = 32'hXXXX_XXXX; // illegal access
            endcase
        end
    end
endmodule

key_vault_rom/sim/tb_key_vault_rom.sv
`timescale 1ns/1ps

module tb_key_vault_rom;

  // DUT inputs
  logic        clk;
  logic        rst_n;
  logic        chip_en;
  logic        read_en;
  logic        zeroize;
  logic [1:0]  word_idx;

  // DUT outputs
  wire [31:0]  data_out;
  wire         oe;
  wire         tamper_latched;
  wire         read_once_latched;

  // Instantiate DUT
  key_vault_rom dut (
    .clk(clk),
    .rst_n(rst_n),
    .chip_en(chip_en),
    .read_en(read_en),
    .zeroize(zeroize),
    .word_idx(word_idx),
    .data_out(data_out),
    .oe(oe),
    .tamper_latched(tamper_latched),
    .read_once_latched(read_once_latched)
  );

  // Simple expect task (4-state aware)
  task automatic tb_expect(string name, logic actual, logic expected);
    if (actual !== expected) begin
      $display("FAIL: %s at t=%0t actual=%b expected=%b", name, $time, actual, expected);
      $finish;
    end else begin
      $display("PASS: %s at t=%0t", name, $time);
    end
  endtask

  task automatic tb_expect32(string name, logic [31:0] actual, logic [31:0] expected);
    if (actual !== expected) begin
      $display("FAIL: %s at t=%0t actual=0x%08h expected=0x%08h", name, $time, actual, expected);
      $finish;
    end else begin
      $display("PASS: %s at t=%0t data=0x%08h", name, $time, actual);
    end
  endtask

  // Pulse a read transaction (one oe rising edge)
  task automatic do_read(input logic [1:0] idx, input logic [31:0] exp_data);
    // set up address while disabled
    @(negedge clk);
    word_idx = idx;

    // start transaction: raise enables before a posedge
    @(negedge clk);
    chip_en = 1'b1;
    read_en = 1'b1;

    // sample on next posedge + small delay
    @(posedge clk); #1;

    tb_expect($sformatf("oe asserted for idx=%0d", idx), oe, 1'b1);
    tb_expect32($sformatf("data_out matches idx=%0d", idx), data_out, exp_data);

    // end transaction: deassert read_en to create a new oe rising edge next time
    @(negedge clk);
    read_en = 1'b0;
    chip_en = 1'b0;

    // allow one posedge to settle
    @(posedge clk); #1;
    tb_expect("oe deasserted after transaction", oe, 1'b0);
  endtask

  // Attempt a read after lockout; expect oe low and data_out zero
  task automatic expect_locked_read(input logic [1:0] idx);
    @(negedge clk);
    word_idx = idx;

    @(negedge clk);
    chip_en = 1'b1;
    read_en = 1'b1;

    @(posedge clk); #1;
    tb_expect($sformatf("oe stays low after lockout idx=%0d", idx), oe, 1'b0);
    tb_expect32("data_out stays zero when disabled", data_out, 32'h0000_0000);

    @(negedge clk);
    read_en = 1'b0;
    chip_en = 1'b0;
  endtask

  // Clock generator
  initial begin
    clk = 0;
    forever #5 clk = ~clk;
  end

  // Monitor (helpful while bringing up)
  initial begin
    $display("time  rst_n chip read zer idx | oe data_out        | tamper read_once");
    $monitor("%4t   %0b    %0b    %0b   %0b  %0d | %0b 0x%08h |   %0b      %0b",
             $time, rst_n, chip_en, read_en, zeroize, word_idx, oe, data_out, tamper_latched, read_once_latched);
  end

  // Main test
  initial begin
    $display("=== Begin ROM TB ===");

    // init
    rst_n   = 1'b0;
    chip_en = 1'b0;
    read_en = 1'b0;
    zeroize = 1'b0;
    word_idx= 2'd0;

    $dumpfile("tb_key_vault_rom.vcd");
    $dumpvars(0, tb_key_vault_rom);

    // reset release
    repeat (2) @(negedge clk);
    rst_n = 1'b1;
    @(posedge clk); #1;

    // Sanity: disabled outputs
    tb_expect("oe low when disabled", oe, 1'b0);
    tb_expect32("data_out zero when disabled", data_out, 32'h0000_0000);
    tb_expect("tamper not latched after reset", tamper_latched, 1'b0);
    tb_expect("read_once not latched after reset", read_once_latched, 1'b0);

    // Read all 4 words (big-endian order)
    do_read(2'd0, 32'h00112233);
    do_read(2'd1, 32'h44556677);
    do_read(2'd2, 32'h8899AABB);
    do_read(2'd3, 32'hCCDDEEFF);

    // After 4 reads, read_once should be latched (may latch at/after 4th read posedge)
    @(posedge clk); #1;
    tb_expect("read_once latched after 4 reads", read_once_latched, 1'b1);

    // 5th read should be blocked
    expect_locked_read(2'd0);

    // Reset again, then test zeroize tamper lock
    $display("=== Reset + zeroize test ===");
    @(negedge clk);
    rst_n = 1'b0;
    chip_en = 1'b0;
    read_en = 1'b0;
    zeroize = 1'b0;
    repeat (2) @(negedge clk);
    rst_n = 1'b1;

    // Trip zeroize
    @(negedge clk);
    zeroize = 1'b1;
    @(posedge clk); #1;
    tb_expect("tamper latched after zeroize", tamper_latched, 1'b1);

    // Attempts should be blocked
    expect_locked_read(2'd2);

    $display("=== ALL ROM TB TESTS PASSED ===");
    $finish;
  end

endmodule

key_vault_rom/build/tb_key_vault_rom.vcd
$date
	Mon Mar  2 09:38:14 2026
$end

$version
	Synopsys VCS version W-2024.09_Full64
$end

$timescale
	1ps
$end

$comment Csum: 1 832b3260d74fa120 $end


$scope module tb_key_vault_rom $end
$var reg 1 ! clk $end
$var reg 1 " rst_n $end
$var reg 1 # chip_en $end
$var reg 1 $ read_en $end
$var reg 1 % zeroize $end
$var reg 2 & word_idx [1:0] $end
$var wire 32 ' data_out [31:0] $end
$var wire 1 ( oe $end
$var wire 1 ) tamper_latched $end
$var wire 1 * read_once_latched $end

$scope module dut $end
$var wire 1 + clk $end
$var wire 1 , rst_n $end
$var wire 1 - chip_en $end
$var wire 1 . read_en $end
$var wire 1 / zeroize $end
$var wire 2 0 word_idx [1:0] $end
$var reg 32 1 data_out [31:0] $end
$var wire 1 ( oe $end
$var reg 1 2 tamper_latched $end
$var reg 1 3 read_once_latched $end
$var reg 2 4 read_count [1:0] $end
$var reg 1 5 oe_d $end
$var reg 1 6 lock_pending $end
$var wire 1 7 read_pulse $end
$upscope $end

$upscope $end

$enddefinitions $end

#0
$dumpvars
0#
0!
0-
0.
03
0,
02
0/
06
0(
05
0$
0*
07
0"
0)
0%
b00000000000000000000000000000000 '
b00000000000000000000000000000000 1
b00 0
b00 4
b00 &
0+
$end
#5000
1!
1+
#10000
0!
0+
#15000
1!
1+
#20000
0!
0+
1"
1,
#25000
1!
1+
#30000
0!
0+
#35000
1!
1+
#40000
0!
0+
1#
1-
1$
1.
1(
17
b00000000000100010010001000110011 1
b00000000000100010010001000110011 '
#45000
1!
1+
15
07
b01 4
#50000
0!
0+
0$
0.
0#
0-
0(
b00000000000000000000000000000000 1
b00000000000000000000000000000000 '
#55000
1!
1+
05
#60000
0!
0+
b01 &
b01 0
#65000
1!
1+
#70000
0!
0+
1#
1-
1$
1.
1(
17
b01000100010101010110011001110111 1
b01000100010101010110011001110111 '
#75000
1!
1+
15
07
b10 4
#80000
0!
0+
0$
0.
0#
0-
0(
b00000000000000000000000000000000 1
b00000000000000000000000000000000 '
#85000
1!
1+
05
#90000
0!
0+
b10 &
b10 0
#95000
1!
1+
#100000
0!
0+
1#
1-
1$
1.
1(
17
b10001000100110011010101010111011 1
b10001000100110011010101010111011 '
#105000
1!
1+
15
07
b11 4
#110000
0!
0+
0$
0.
0#
0-
0(
b00000000000000000000000000000000 1
b00000000000000000000000000000000 '
#115000
1!
1+
05
#120000
0!
0+
b11 &
b11 0
#125000
1!
1+
#130000
0!
0+
1#
1-
1$
1.
1(
17
b11001100110111011110111011111111 1
b11001100110111011110111011111111 '
#135000
1!
1+
15
07
16
#140000
0!
0+
0$
0.
0#
0-
0(
b00000000000000000000000000000000 1
b00000000000000000000000000000000 '
#145000
1!
1+
05
13
1*
06
#150000
0!
0+
#155000
1!
1+
#160000
0!
0+
b00 &
b00 0
#165000
1!
1+
#170000
0!
0+
1#
1-
1$
1.
#175000
1!
1+
#180000
0!
0+
0$
0.
0#
0-
#185000
1!
1+
#190000
0!
0+
0"
0,
03
0*
b00 4
#195000
1!
1+
#200000
0!
0+
#205000
1!
1+
#210000
0!
0+
1"
1,
#215000
1!
1+
#220000
0!
0+
1%
1/
#225000
1!
1+
12
1)
13
1*
#230000
0!
0+
b10 &
b10 0
#235000
1!
1+
#240000
0!
0+
1#
1-
1$
1.
#245000
1!
1+
#250000
0!
0+
0$
0.
0#
0-
