aes_input_buffer/rtl/aes_input_block_buffer.v
`timescale 1ns/1ps
module aes_input_block_buffer #(
    parameter int SIZE = 128
)(
    input logic clk,
    input logic reset,
    input logic zeroize,
    input logic wr_en,
    input logic [1:0] wr_addr,
    input logic [31:0] wr_data,
    output logic [SIZE-1:0] block_in,
    output logic [3:0] valid_mask,
    output logic all_valid
);

    // internal words
    logic [31:0] w0, w1, w2, w3;
    assign block_in = {w0,w1,w2,w3};
    assign all_valid = &valid_mask;

    always_ff @(posedge clk) begin
        if (reset || zeroize) begin
            w0 <= '0; w1 <= '0; w2 <= '0; w3 <= '0;
            valid_mask <= 4'b0000;    
        end
        else begin
            if (wr_en) begin
                unique case (wr_addr)
                    2'd0: begin w0 <= wr_data; valid_mask[0] <= 1'b1; end
                    2'd1: begin w1 <= wr_data; valid_mask[1] <= 1'b1; end
                    2'd2: begin w2 <= wr_data; valid_mask[2] <= 1'b1; end
                    2'd3: begin w3 <= wr_data; valid_mask[3] <= 1'b1; end
                    default:; // UNREACHABLE
                endcase
            end
        end
    end
endmodule

aes_input_buffer/sim/tb_aes_input_block_buffer.sv
`timescale 1ns/1ps
module tb_aes_input_block_buffer;
    localparam int unsigned SIZE = 128;

    // DUT inputs 
    logic clk;
    logic reset;
    logic zeroize;  
    logic wr_en;
    logic [1:0] wr_addr;
    logic [31:0] wr_data;

    // DUT outputs
    logic [SIZE-1:0] block_in;
    logic [3:0] valid_mask;
    logic all_valid;

    // init DUT
    aes_input_block_buffer #(.SIZE(SIZE)) dut (
        .clk(clk),
        .reset(reset),
        .zeroize(zeroize),
        .wr_en(wr_en),
        .wr_addr(wr_addr),
        .wr_data(wr_data),
        .block_in(block_in),
        .valid_mask(valid_mask),
        .all_valid(all_valid)
    );

    // clock
    initial begin
        clk = 1'b0;
        forever #5 clk = ~clk;
    end

    // helper tasks
    task automatic tb_expect_bit(string name, logic actual, logic expected);
        if (actual !== expected) begin
            $display("FAIL: %s at t=%0t actual=%b expected=%b", name, $time, actual, expected);
            $finish;
        end
        else begin  
            $display("PASS: %s at t=%0t", name, $time);
        end
    endtask

    task automatic tb_expect_mask(string name, logic [3:0] actual, logic [3:0] expected);
        if (actual !== expected) begin
            $display("FAIL: %s at t=%0t actual=%b expected=%b", name, $time, actual, expected);
            $finish;
        end
        else begin
            $display("PASS: %s at t=%0t", name, $time);
        end
    endtask

    task automatic tb_expect_vec128(string name, logic [127:0] actual, logic [127:0] expected);
        if (actual !== expected) begin
            $display("FAIL: %s at t=%0t actual=%h expected=%h", name, $time, actual, expected);
            $finish;
        end
        else begin
            $display("PASS: %s at t=%0t", name, $time);
        end
    endtask

    task automatic do_reset();
        begin
            @(negedge clk);
            reset = 1'b1;
            zeroize = 1'b0;
            wr_en = 1'b0;
            @(negedge clk);
            @(negedge clk);
            reset = 1'b0;
            @(posedge clk); #1;
        end
    endtask

    task automatic write_word(input logic [1:0] addr, input logic [31:0] data);
        begin
            @(negedge clk); 
            wr_addr = addr;
            wr_data = data;
            wr_en = 1'b1;
            @(negedge clk);
            wr_en = 1'b0;
        end
    endtask


    // test sequence
    initial begin
        $display("=== aes_input_block_buffer TB ===");
        reset = 1'b0;
        zeroize = 1'b0;
        wr_en = 1'b0;
        wr_data = 32'h0;
        $dumpfile("tb_aes_input_block_buffer.vcd");
        $dumpvars(0, tb_aes_input_block_buffer);
        $display("Test 1: reset clears buffer");
        do_reset();
        tb_expect_mask("reset: valid_mask=0000", valid_mask, 4'b0000);
        tb_expect_bit("reset: all_valid=0", all_valid, 1'b0);
        tb_expect_vec128("reset: block_in=0", block_in, 128'h0);        
        $display("Test 1: Pass");
    
        $display("Test 2: Partial Write");
        do_reset();
        
        write_word(2'd0, 32'hDEADBEEF);
        write_word(2'd1, 32'hCAFEBABE);
    
        @(posedge clk); #1;
        tb_expect_mask("partial write: valid_mask=0011", valid_mask, 4'b0011);
        tb_expect_bit("partial write: all_valid=0", all_valid, 1'b0);
        tb_expect_vec128("partial_write: block_in=DEADBEEF_CAFEBABE_00000000_00000000", block_in, 128'hDEADBEEF_CAFEBABE_00000000_00000000);

        $display("Test 2: Pass");

        $display("Test 3: Full Write");
        do_reset();
        write_word(2'd0, 32'h00112233);
        write_word(2'd1, 32'h44556677);
        write_word(2'd2, 32'h8899AABB);
        write_word(2'd3, 32'hCCDDEEFF);
        @(posedge clk); #1;
        tb_expect_mask("full write: valid_mask=1111", valid_mask, 4'b1111);
        tb_expect_bit("full write: all_valid", all_valid, 1'b1);
        tb_expect_vec128("full write: block_in fully written", block_in, 128'h00112233_44556677_8899AABB_CCDDEEFF);
        $display("Test 3: Pass");
        
        $display("Test 4: overwrite behavior");
        do_reset();
        
        // orig write 
        
        write_word(2'd0, 32'hDEADBEEF);
        write_word(2'd1, 32'hCAFEBABE);

        @(posedge clk); #1;
        tb_expect_mask("partial write: valid_mask=0011", valid_mask, 4'b0011);
        tb_expect_bit("partial write: all_valid=0", all_valid, 1'b0);
        tb_expect_vec128("partial_write: block_in=DEADBEEF_CAFEBABE_00000000_00000000", block_in, 128'hDEADBEEF_CAFEBABE_00000000_00000000);

        //@(posedge clk); #1;
        // overwrite
        write_word(2'd0, 32'h11223344);
        write_word(2'd1, 32'hCAFEBABE);

        @(posedge clk); #1;
        tb_expect_mask("partial write: valid_mask=0011", valid_mask, 4'b0011);
        tb_expect_bit("partial write: all_valid=0", all_valid, 1'b0);
        tb_expect_vec128("partial_write: block_in=11223344_CAFEBABE_00000000_00000000", block_in, 128'h11223344_CAFEBABE_00000000_00000000);        
        $display("Test 4: Pass");


        $display("Test 5: zeroize");
        do_reset();
        write_word(2'd0, 32'h00112233);
        write_word(2'd1, 32'h44556677);
        write_word(2'd2, 32'h8899AABB);
        write_word(2'd3, 32'hCCDDEEFF);
        @(posedge clk); #1;
        tb_expect_mask("before zeroize: valid_mask=1111", valid_mask, 4'b1111);
        tb_expect_bit("before zeroize: all_valid", all_valid, 1'b1);
        tb_expect_vec128("before zeroize: block_in fully written", block_in, 128'h11223344_55667788_99AABBCC_DDEEFF);
        @(negedge clk);
        zeroize = 1'b1;
        @(negedge clk);
        zeroize = 1'b0;
        @(posedge clk); #1;
        tb_expect_mask("after zeroize: valid_mask=0000", valid_mask, 4'b0000);       
        tb_expect_bit("after zeroize: all_valid=0", all_valid, 1'b0);
        tb_expect_vec128("after zeroize: block_in=0", block_in, 128'd0);
        $display("Test 5: Pass");

        $display("=== All tests passed ===");
        $finish;
    end

endmodule

aes_input_buffer/build/tb_aes_input_block_buffer.vcd
$date
	Thu Mar 19 15:45:42 2026
$end

$version
	Synopsys VCS version W-2024.09_Full64
$end

$timescale
	1ps
$end

$comment Csum: 1 d95181c8ba25cadf $end


$scope module tb_aes_input_block_buffer $end
$var reg 1 ! clk $end
$var reg 1 " reset $end
$var reg 1 # zeroize $end
$var reg 1 $ wr_en $end
$var reg 2 % wr_addr [1:0] $end
$var reg 32 & wr_data [31:0] $end
$var reg 128 ' block_in [127:0] $end
$var reg 4 ( valid_mask [3:0] $end
$var reg 1 ) all_valid $end

$scope module dut $end
$var reg 1 ! clk $end
$var reg 1 " reset $end
$var reg 1 # zeroize $end
$var reg 1 $ wr_en $end
$var reg 2 % wr_addr [1:0] $end
$var reg 32 & wr_data [31:0] $end
$var reg 128 ' block_in [127:0] $end
$var reg 4 ( valid_mask [3:0] $end
$var reg 1 ) all_valid $end
$var reg 32 * w0 [31:0] $end
$var reg 32 + w1 [31:0] $end
$var reg 32 , w2 [31:0] $end
$var reg 32 - w3 [31:0] $end
$upscope $end

$upscope $end

$enddefinitions $end

#0
$dumpvars
x)
0!
0"
0$
0#
bxxxxxxxxxxxxxxxxxxxxxxxxxxxxxxxxxxxxxxxxxxxxxxxxxxxxxxxxxxxxxxxxxxxxxxxxxxxxxxxxxxxxxxxxxxxxxxxxxxxxxxxxxxxxxxxxxxxxxxxxxxxxxxxx '
bxxxx (
bxxxxxxxxxxxxxxxxxxxxxxxxxxxxxxxx *
bxxxxxxxxxxxxxxxxxxxxxxxxxxxxxxxx +
bxxxxxxxxxxxxxxxxxxxxxxxxxxxxxxxx ,
bxxxxxxxxxxxxxxxxxxxxxxxxxxxxxxxx -
bxx %
b00000000000000000000000000000000 &
$end
#5000
1!
#10000
0!
1"
#15000
1!
b00000000000000000000000000000000 *
b00000000000000000000000000000000xxxxxxxxxxxxxxxxxxxxxxxxxxxxxxxxxxxxxxxxxxxxxxxxxxxxxxxxxxxxxxxxxxxxxxxxxxxxxxxxxxxxxxxxxxxxxxxx '
b00000000000000000000000000000000 +
b0000000000000000000000000000000000000000000000000000000000000000xxxxxxxxxxxxxxxxxxxxxxxxxxxxxxxxxxxxxxxxxxxxxxxxxxxxxxxxxxxxxxxx '
b00000000000000000000000000000000 ,
b000000000000000000000000000000000000000000000000000000000000000000000000000000000000000000000000xxxxxxxxxxxxxxxxxxxxxxxxxxxxxxxx '
b00000000000000000000000000000000 -
b00000000000000000000000000000000000000000000000000000000000000000000000000000000000000000000000000000000000000000000000000000000 '
b0000 (
0)
#20000
0!
#25000
1!
#30000
0!
0"
#35000
1!
#40000
0!
1"
#45000
1!
#50000
0!
#55000
1!
#60000
0!
0"
#65000
1!
#70000
0!
b00 %
b11011110101011011011111011101111 &
1$
#75000
1!
b11011110101011011011111011101111 *
b11011110101011011011111011101111000000000000000000000000000000000000000000000000000000000000000000000000000000000000000000000000 '
b0001 (
#80000
0!
0$
#85000
1!
#90000
0!
b01 %
b11001010111111101011101010111110 &
1$
#95000
1!
b11001010111111101011101010111110 +
b11011110101011011011111011101111110010101111111010111010101111100000000000000000000000000000000000000000000000000000000000000000 '
b0011 (
#100000
0!
0$
#105000
1!
#110000
0!
1"
#115000
1!
b00000000000000000000000000000000 *
b00000000000000000000000000000000110010101111111010111010101111100000000000000000000000000000000000000000000000000000000000000000 '
b00000000000000000000000000000000 +
b00000000000000000000000000000000000000000000000000000000000000000000000000000000000000000000000000000000000000000000000000000000 '
b0000 (
#120000
0!
#125000
1!
#130000
0!
0"
#135000
1!
#140000
0!
b00 %
b00000000000100010010001000110011 &
1$
#145000
1!
b00000000000100010010001000110011 *
b00000000000100010010001000110011000000000000000000000000000000000000000000000000000000000000000000000000000000000000000000000000 '
b0001 (
#150000
0!
0$
#155000
1!
#160000
0!
b01 %
b01000100010101010110011001110111 &
1$
#165000
1!
b01000100010101010110011001110111 +
b00000000000100010010001000110011010001000101010101100110011101110000000000000000000000000000000000000000000000000000000000000000 '
b0011 (
#170000
0!
0$
#175000
1!
#180000
0!
b10 %
b10001000100110011010101010111011 &
1$
#185000
1!
b10001000100110011010101010111011 ,
b00000000000100010010001000110011010001000101010101100110011101111000100010011001101010101011101100000000000000000000000000000000 '
b0111 (
#190000
0!
0$
#195000
1!
#200000
0!
b11 %
b11001100110111011110111011111111 &
1$
#205000
1!
b11001100110111011110111011111111 -
b00000000000100010010001000110011010001000101010101100110011101111000100010011001101010101011101111001100110111011110111011111111 '
b1111 (
1)
#210000
0!
0$
#215000
1!
#220000
0!
1"
#225000
1!
b00000000000000000000000000000000 *
b00000000000000000000000000000000010001000101010101100110011101111000100010011001101010101011101111001100110111011110111011111111 '
b00000000000000000000000000000000 +
b00000000000000000000000000000000000000000000000000000000000000001000100010011001101010101011101111001100110111011110111011111111 '
b00000000000000000000000000000000 ,
b00000000000000000000000000000000000000000000000000000000000000000000000000000000000000000000000011001100110111011110111011111111 '
b00000000000000000000000000000000 -
b00000000000000000000000000000000000000000000000000000000000000000000000000000000000000000000000000000000000000000000000000000000 '
b0000 (
0)
#230000
0!
#235000
1!
#240000
0!
0"
#245000
1!
#250000
0!
b00 %
b11011110101011011011111011101111 &
1$
#255000
1!
b11011110101011011011111011101111 *
b11011110101011011011111011101111000000000000000000000000000000000000000000000000000000000000000000000000000000000000000000000000 '
b0001 (
#260000
0!
0$
#265000
1!
#270000
0!
b01 %
b11001010111111101011101010111110 &
1$
#275000
1!
b11001010111111101011101010111110 +
b11011110101011011011111011101111110010101111111010111010101111100000000000000000000000000000000000000000000000000000000000000000 '
b0011 (
#280000
0!
0$
#285000
1!
#290000
0!
b00 %
b00010001001000100011001101000100 &
1$
#295000
1!
b00010001001000100011001101000100 *
b00010001001000100011001101000100110010101111111010111010101111100000000000000000000000000000000000000000000000000000000000000000 '
#300000
0!
0$
#305000
1!
#310000
0!
b01 %
b11001010111111101011101010111110 &
1$
#315000
1!
#320000
0!
0$
#325000
1!
#330000
0!
1"
#335000
1!
b00000000000000000000000000000000 *
b00000000000000000000000000000000110010101111111010111010101111100000000000000000000000000000000000000000000000000000000000000000 '
b00000000000000000000000000000000 +
b00000000000000000000000000000000000000000000000000000000000000000000000000000000000000000000000000000000000000000000000000000000 '
b0000 (
#340000
0!
#345000
1!
#350000
0!
0"
#355000
1!
#360000
0!
b00 %
b00000000000100010010001000110011 &
1$
#365000
1!
b00000000000100010010001000110011 *
b00000000000100010010001000110011000000000000000000000000000000000000000000000000000000000000000000000000000000000000000000000000 '
b0001 (
#370000
0!
0$
#375000
1!
#380000
0!
b01 %
b01000100010101010110011001110111 &
1$
#385000
1!
b01000100010101010110011001110111 +
b00000000000100010010001000110011010001000101010101100110011101110000000000000000000000000000000000000000000000000000000000000000 '
b0011 (
#390000
0!
0$
#395000
1!
#400000
0!
b10 %
b10001000100110011010101010111011 &
1$
#405000
1!
b10001000100110011010101010111011 ,
b00000000000100010010001000110011010001000101010101100110011101111000100010011001101010101011101100000000000000000000000000000000 '
b0111 (
#410000
0!
0$
#415000
1!
#420000
0!
b11 %
b11001100110111011110111011111111 &
1$
#425000
1!
b11001100110111011110111011111111 -
b00000000000100010010001000110011010001000101010101100110011101111000100010011001101010101011101111001100110111011110111011111111 '
b1111 (
1)
#430000
0!
0$
#435000
1!
#440000
0!
1#
#445000
1!
b00000000000000000000000000000000 *
b00000000000000000000000000000000010001000101010101100110011101111000100010011001101010101011101111001100110111011110111011111111 '
b00000000000000000000000000000000 +
b00000000000000000000000000000000000000000000000000000000000000001000100010011001101010101011101111001100110111011110111011111111 '
b00000000000000000000000000000000 ,
b00000000000000000000000000000000000000000000000000000000000000000000000000000000000000000000000011001100110111011110111011111111 '
b00000000000000000000000000000000 -
b00000000000000000000000000000000000000000000000000000000000000000000000000000000000000000000000000000000000000000000000000000000 '
b0000 (
0)
#450000
0!
0#
