comparator/rtl/key_activation_compare.v
`timescale 1ns/1ps
module key_activation_compare #(
    parameter int SIZE = 128
)(
    input logic [SIZE-1:0] key_in, // input written to key buffer from CPU
    input logic [SIZE-1:0] key_hw, // key in use
    output logic match 
);
    logic [SIZE-1:0] diff;
    // compare full vector -> no early exists causing comprimised security
    assign diff = key_in ^ key_hw; // input key XOR hw key
    assign match = ~(|diff); 
endmodule

key_commit_buffer/rtl/key_commit_buffer.v
`timescale 1ns/1ps

module key_commit_buffer #(
    parameter int SIZE = 128
)(
    input  logic             clk,
    input  logic             reset,
    input  logic             zeroize,       // wipes buffer + status

    // 32-bit write interface
    input  logic             wr_en,
    input  logic [1:0]       wr_addr,
    input  logic [31:0]      wr_data,

    // commit pulse
    input  logic             commit,

    // hardware key to compare against
    input  logic [SIZE-1:0]  key_hw,

    // outputs
    output logic [SIZE-1:0]  key_in,         // assembled key
    output logic [3:0]       valid_mask,     // which words have been written
    output logic             all_valid,
    output logic             do_compare,     // 1-cycle pulse when compare performed
    output logic             match_q,        // latched compare result
    output logic             commit_illegal
);

    // internal words
    logic [31:0] w0, w1, w2, w3;

    // comparator output
    logic match;

    // big-endian assembly (w0 is MSW)
    assign key_in = {w0,w1,w2,w3};

    assign all_valid = &valid_mask;

    // comparator
    key_activation_compare #(.SIZE(SIZE)) u_cmp (
        .key_in(key_in),
        .key_hw(key_hw),
        .match(match)
    );

    // sequential logic
    always_ff @(posedge clk) begin
        if (reset || zeroize) begin
            w0 <= '0; w1 <= '0; w2 <= '0; w3 <= '0;
            valid_mask     <= 4'b0000;
            do_compare     <= 1'b0;
            match_q        <= 1'b0;
            commit_illegal <= 1'b0;
        end else begin
            // defaults
            do_compare     <= 1'b0;
            commit_illegal <= 1'b0;

            // writes
            if (wr_en && !commit) begin
                unique case (wr_addr)
                    2'd0: begin w0 <= wr_data; valid_mask[0] <= 1'b1; end
                    2'd1: begin w1 <= wr_data; valid_mask[1] <= 1'b1; end
                    2'd2: begin w2 <= wr_data; valid_mask[2] <= 1'b1; end
                    2'd3: begin w3 <= wr_data; valid_mask[3] <= 1'b1; end
                    default: /* unreachable */ ;
                endcase
            end

            // commit: compare only if all 4 words are valid
            if (commit) begin
                if (all_valid) begin
                    do_compare <= 1'b1;
                    match_q    <= match;
                end else begin
                    commit_illegal <= 1'b1;
                    match_q        <= 1'b0; // fail-closed
                end
            end
        end
    end

endmodule

key_commit_buffer/sim/tb_key_commit_buffer.sv
`timescale 1ns/1ps

module tb_key_commit_buffer;

    localparam int unsigned SIZE = 128;
    // DUT inputs

    logic clk;
    logic reset;
    logic zeroize;
    
    logic wr_en;
    logic [31:0] wr_data;
    logic [1:0] wr_addr;

    logic commit;
    logic [SIZE-1:0] key_hw;

    // DUT outputs
    logic [SIZE-1:0] key_in;
    logic [3:0] valid_mask;
    logic all_valid;
    logic do_compare;
    logic match_q;
    logic commit_illegal;

    // init DUT
    key_commit_buffer #(.SIZE(SIZE)) dut (
        .clk(clk),
        .reset(reset),
        .zeroize(zeroize),
        .wr_en(wr_en),
        .wr_addr(wr_addr),
        .wr_data(wr_data),
        .commit(commit),
        .key_hw(key_hw),
        .key_in(key_in),
        .valid_mask(valid_mask),
        .all_valid(all_valid),
        .do_compare(do_compare),
        .match_q(match_q),
        .commit_illegal(commit_illegal)
    );


    // generate clock signal
    initial begin
        clk = 1'b0;
        forever #5 clk = ~clk; // 5ns 
    end

    // expect bit helpers

    task automatic tb_expect_bit(string name, logic actual, logic expected);
        if (actual !== expected) begin
            $display("FAIL: %s at %t actual=%h expected=%h",name,$time,actual,expected);
            $finish;
        end
        else begin
            $display("PASS: %s at t=%0t", name, $time);    
        end
    endtask
     
    
    task automatic tb_expect_vec128(string name, logic [127:0] actual, logic [127:0] expected);
        if (actual !== expected) begin
            $display("FAIL: %s at t=%0t actual=%h expected=%h", name, $time, actual, expected);
            $finish;
        end else begin
            $display("PASS: %s at t=%0t", name, $time);
        end
    endtask

    task automatic tb_expect_mask(string name, logic [3:0] actual, logic [3:0] expected);
        if (actual !== expected) begin
            $display("FAIL: %s at t=%0t actual=%h expected=%h", name, $time, actual, expected);
            $finish;
        end else begin
            $display("PASS: %s at t=%0t", name, $time);
        end
    endtask

    // bus helpers (place holders for real signals)
    task automatic do_reset();
        begin
          @(negedge clk);
          reset   = 1'b1;
          zeroize = 1'b0;
          wr_en   = 1'b0;
          commit  = 1'b0;
          @(negedge clk);
          @(negedge clk);
          reset   = 1'b0;
          @(negedge clk);
        end
    endtask

    task automatic write_word(input logic [1:0] addr, input logic [31:0] data);
        begin
            @(negedge clk)
            wr_addr = addr;
            wr_data = data;
            wr_en = 1'b1;
            commit = 1'b0;
            @(negedge clk);
            wr_en = 1'b0;
        end
    endtask

    task automatic do_commit();
        begin
            @(negedge clk);
            commit  = 1'b1;
            wr_en = 1'b0;
            @(posedge clk); #1;
            @(negedge clk);
            commit = 1'b0;
        end
    endtask

    // handler if commit and write on same cycle ( commit should win)
    task automatic commit_conflicts_write(input logic [1:0] addr, input logic [31:0] data);
        begin
            @(negedge clk);
            wr_addr = addr;
            wr_data = data;
            wr_en = 1'b1;
            commit = 1'b1;
            @(posedge clk); #1;
            @(negedge clk);
            wr_en = 1'b0;
            commit = 1'b0;
        end
    endtask

    task automatic sample_idle_outputs(string tag);
        begin
            @(posedge clk); #1; 
            tb_expect_bit({tag, ": do compare low"}, do_compare, 1'b0);
            tb_expect_bit({tag, ": commit_illegal low"}, commit_illegal, 1'b0);
        end
    endtask


    // test sequence
    initial begin
        $display(" === begin test squenece ===");
        // initial inputs
        reset = 1'b0;
        zeroize = 1'b0;
        wr_en = 1'b0;
        wr_addr = 2'd0;
        wr_data = 32'h0;
        commit = 1'b0;

        // built in hw key -> big endian
        key_hw = 128'h00112233_44556677_8899AABB_CCDDEEFF;
        $dumpfile("tb_key_commit_buffer.vcd");
        $dumpvars(0, tb_key_commit_buffer);
        
        // 1.) reset
        $display("Test 1: Reset");
        do_reset(); // use do reset task
        tb_expect_mask("reset: valid_mask=0000", valid_mask, 4'b0000);
        tb_expect_bit("reset: all_valid=0", all_valid, 1'b0);
        tb_expect_bit("reset: do_compare=0",do_compare, 1'b0);
        tb_expect_bit("reset match_q=0",match_q,1'b0);
        tb_expect_bit("reset: commit illegal=0",commit_illegal,1'b0);
        tb_expect_vec128("reset: key_in=0", key_in, 128'h0);
        $display("Test 1: PASS");

        // 2.) partial write + commit -> expect illegal
        $display("Test 2: Partial Write then commit (expect illegal)");
        do_reset();
        write_word(2'd0, 32'h00112233);
        write_word(2'd1, 32'h44556677);
        @(posedge clk); #1;
        tb_expect_mask("partial: valid_mask=0011", valid_mask, 4'b0011);
        tb_expect_bit("partial: all_valid=0", all_valid, 1'b0);
        do_commit();
        tb_expect_bit("partial: do_compare=0",do_compare,1'b0);
        tb_expect_bit("partial: commit_illegal=1 (pulsed)",commit_illegal, 1'b1);
        tb_expect_bit("partial: match_q=0 fail-closed",match_q,1'b0);
        @(posedge clk); #1;
        tb_expect_bit("partial: commit_illegal back to 0 on following cycle",commit_illegal,1'b0);
        tb_expect_bit("partial: do_compare stays 0 next cycle",do_compare,1'b0);
        $display("Test 2: Passed");
        
        $display("Test 3: Correct Key Written");
        do_reset();
        write_word(2'd0, 32'h00112233);
        write_word(2'd1, 32'h44556677);
        write_word(2'd2, 32'h8899AABB);
        write_word(2'd3, 32'hCCDDEEFF);
        @(posedge clk); #1;
        tb_expect_mask("full: valid_mask=1111", valid_mask, 4'b1111);
        tb_expect_bit("full: all_valid=1", all_valid, 1'b1);
        tb_expect_vec128("full: key_in matches ROM key", key_in, key_hw);
        do_commit();
        tb_expect_bit("full: do_compare=1 (pulsed)", do_compare, 1'b1);
        tb_expect_bit("full: commit_illegal=0", commit_illegal, 1'b0);
        tb_expect_bit("full: match_q=1", match_q, 1'b1);
        @(posedge clk); #1;
        tb_expect_bit("full: do_compare back to 0 next cycle", do_compare, 1'b0);        
        tb_expect_bit("full: commit_illegal; stays 0 next cycle", commit_illegal, 1'b0);        
        tb_expect_bit("full: match_q stays 1 after pulse", match_q, 1'b1);        
        $display("Test 3: Passed");

        $display("Test 4: Mismatched Key");
        do_reset();
        // 1 bit difference -> should be caught by XOR compare
        write_word(2'd0, 32'h00112233);
        write_word(2'd1, 32'h44556677);
        write_word(2'd2, 32'h8899AABB);
        write_word(2'd3, 32'hCCDDEEFE);
        @(posedge clk); #1;
        tb_expect_mask("wrong: valid mask=1111", valid_mask, 4'b1111);
        tb_expect_bit("wrong: all_valid=1", all_valid, 1'b1);
        do_commit();
        tb_expect_bit("wrong: do_compare=1 (pulsed)", do_compare, 1'b1);        
        tb_expect_bit("wrong: commit_illegal=0", commit_illegal, 1'b0);
        tb_expect_bit("wrong: match_q=0", match_q, 1'b0);
        @(posedge clk); #1;
        tb_expect_bit("wrong: do_compare back to 0", do_compare, 1'b0);
        tb_expect_bit("wrong: commit_illegal stays 0 next cycle", commit_illegal, 1'b0);
        tb_expect_bit("wrong: match_q=after pulse", match_q, 1'b0);        

        $display("Test 4: Pass");

        // 5.) wr_en / commit asserted in the same cycle (expect commit to win)
        $display("Test 5: Commit wins over write conflict (expect illegal if not all_valid)");
        do_reset();
        // write 3/4 words -> not all valid
        write_word(2'd0, 32'h00112233);
        write_word(2'd1, 32'h44556677);
        write_word(2'd2, 32'h8899AABB);        
        @(posedge clk); #1;
        tb_expect_mask("conflict: valid_mask=0111 before conflict", valid_mask, 4'b0111);
        tb_expect_bit("conflict: all_valid=0 before conflict", all_valid, 1'b0);
        // call handler for conflict
        commit_conflicts_write(2'd3, 32'hCCDDEEFF);
        // check vectors
        tb_expect_bit("conflict: do_compare=0", do_compare, 1'b0);
        tb_expect_bit("conflict: commit_illegal=1 (pulsed)", commit_illegal, 1'b1);
        tb_expect_bit("conflict: match_q=0 fail-closed", match_q, 1'b0);
        tb_expect_mask("conflict: valid_mask still 0111 (ignored last write)", valid_mask, 4'b0111);     
        // next cycle pulse should drop
        @(posedge clk); #1;
        tb_expect_bit("conflict: commit_illegal back to 0 next cycle", commit_illegal, 1'b0);
        tb_expect_bit("conflict: do_compare stays 0 next cycle", do_compare, 1'b0);
        $display("Test 5: Passed");

        $display("Test 6: Zeroize");
        // reset -> write keyword -> commit
        do_reset();
        write_word(2'd0, 32'h00112233);
        write_word(2'd1, 32'h44556677);
        write_word(2'd2, 32'h8899AABB);
        write_word(2'd3, 32'hCCDDEEFF);
        do_commit();

        tb_expect_bit("pre-zeroize: do_compare=1", do_compare, 1'b1);
        tb_expect_bit("pre-zeroize: match_q=1", match_q, 1'b1);
        tb_expect_mask("pre-zeroize: valid_mask=1111", valid_mask, 4'b1111);

        // Commit performed, now zero the circuit
        @(negedge clk);
        zeroize = 1'b1;
        @(negedge clk);
        zeroize = 1'b0;

        tb_expect_mask("zeroized: valid_mask=0000", valid_mask,4'b0000);
        tb_expect_bit("zeroized: all_valid=0",all_valid, 1'b0);
        tb_expect_vec128("zeroized: key_in=0",key_in,128'h0);
        tb_expect_bit("zeroized: match_q=0", match_q, 1'b0);        
        tb_expect_bit("zeroized: do_compare=0", do_compare, 1'b0);        
        tb_expect_bit("zeroized: commit_illegal=0", commit_illegal, 1'b0);        
         
        $display("Test 6: Passed");

        $display("=== All Tests Passed ===");        
        $finish;
    end


    // Assertions
    
    // do_compare must be a 1 cyc pulse
    assert property(@(posedge clk) do_compare |-> ##1 !do_compare);
    
    // commit illegal must be a 1 cyc pulse
    assert property (@(posedge clk) commit_illegal |-> ##1 !commit_illegal);
    
    // illegal commit must never trigger compare
    assert property (@(posedge clk) commit_illegal |-> !do_compare);
    
    // if commit occurs while not all_valid, commit_illegal must assert
    assert property (@(posedge clk)
        (commit && !all_valid) |-> commit_illegal 
    );  

endmodule

key_commit_buffer/build/tb_key_commit_buffer.vcd
$date
	Wed Mar 18 14:41:40 2026
$end

$version
	Synopsys VCS version W-2024.09_Full64
$end

$timescale
	1ps
$end

$comment Csum: 1 930173ca71faaaec $end


$scope module tb_key_commit_buffer $end
$var reg 1 ! commit $end
$var reg 1 " all_valid $end
$var reg 1 # do_compare $end
$var reg 1 $ commit_illegal $end
$var reg 1 % clk $end
$var reg 1 & reset $end
$var reg 1 ' zeroize $end
$var reg 1 ( wr_en $end
$var reg 32 ) wr_data [31:0] $end
$var reg 2 * wr_addr [1:0] $end
$var reg 128 + key_hw [127:0] $end
$var reg 128 , key_in [127:0] $end
$var reg 4 - valid_mask [3:0] $end
$var reg 1 . match_q $end

$scope task _$$txp______assert_unnamed$$_2 $end
$upscope $end


$scope task _$$txp______assert_unnamed$$_3 $end
$upscope $end


$scope task _$$txp______assert_unnamed$$_4 $end
$upscope $end


$scope task _$$txp______assert_unnamed$$_5 $end
$upscope $end


$scope module dut $end
$var reg 1 % clk $end
$var reg 1 & reset $end
$var reg 1 ' zeroize $end
$var reg 1 ( wr_en $end
$var reg 2 * wr_addr [1:0] $end
$var reg 32 ) wr_data [31:0] $end
$var reg 1 ! commit $end
$var reg 128 + key_hw [127:0] $end
$var reg 128 , key_in [127:0] $end
$var reg 4 - valid_mask [3:0] $end
$var reg 1 " all_valid $end
$var reg 1 # do_compare $end
$var reg 1 . match_q $end
$var reg 1 $ commit_illegal $end
$var reg 32 / w0 [31:0] $end
$var reg 32 0 w1 [31:0] $end
$var reg 32 1 w2 [31:0] $end
$var reg 32 2 w3 [31:0] $end
$var reg 1 3 match $end

$scope module u_cmp $end
$var reg 128 , key_in [127:0] $end
$var reg 128 + key_hw [127:0] $end
$var reg 1 3 match $end
$var reg 128 4 diff [127:0] $end
$upscope $end

$upscope $end

$upscope $end

$enddefinitions $end

#0
$dumpvars
x"
0%
0!
x$
x#
x3
x.
0&
0(
0'
b00000000000100010010001000110011010001000101010101100110011101111000100010011001101010101011101111001100110111011110111011111111 +
bxxxxxxxxxxxxxxxxxxxxxxxxxxxxxxxxxxxxxxxxxxxxxxxxxxxxxxxxxxxxxxxxxxxxxxxxxxxxxxxxxxxxxxxxxxxxxxxxxxxxxxxxxxxxxxxxxxxxxxxxxxxxxxxx ,
bxxxxxxxxxxxxxxxxxxxxxxxxxxxxxxxxxxxxxxxxxxxxxxxxxxxxxxxxxxxxxxxxxxxxxxxxxxxxxxxxxxxxxxxxxxxxxxxxxxxxxxxxxxxxxxxxxxxxxxxxxxxxxxxx 4
bxxxx -
bxxxxxxxxxxxxxxxxxxxxxxxxxxxxxxxx /
bxxxxxxxxxxxxxxxxxxxxxxxxxxxxxxxx 0
bxxxxxxxxxxxxxxxxxxxxxxxxxxxxxxxx 1
bxxxxxxxxxxxxxxxxxxxxxxxxxxxxxxxx 2
b00 *
b00000000000000000000000000000000 )
$end
#5000
1%
0#
0$
#10000
0%
1&
#15000
1%
b00000000000000000000000000000000 /
b00000000000100010010001000110011xxxxxxxxxxxxxxxxxxxxxxxxxxxxxxxxxxxxxxxxxxxxxxxxxxxxxxxxxxxxxxxxxxxxxxxxxxxxxxxxxxxxxxxxxxxxxxxx 4
b00000000000000000000000000000000xxxxxxxxxxxxxxxxxxxxxxxxxxxxxxxxxxxxxxxxxxxxxxxxxxxxxxxxxxxxxxxxxxxxxxxxxxxxxxxxxxxxxxxxxxxxxxxx ,
b00000000000000000000000000000000 0
b0000000000010001001000100011001101000100010101010110011001110111xxxxxxxxxxxxxxxxxxxxxxxxxxxxxxxxxxxxxxxxxxxxxxxxxxxxxxxxxxxxxxxx 4
b0000000000000000000000000000000000000000000000000000000000000000xxxxxxxxxxxxxxxxxxxxxxxxxxxxxxxxxxxxxxxxxxxxxxxxxxxxxxxxxxxxxxxx ,
b00000000000000000000000000000000 1
b000000000001000100100010001100110100010001010101011001100111011110001000100110011010101010111011xxxxxxxxxxxxxxxxxxxxxxxxxxxxxxxx 4
b000000000000000000000000000000000000000000000000000000000000000000000000000000000000000000000000xxxxxxxxxxxxxxxxxxxxxxxxxxxxxxxx ,
b00000000000000000000000000000000 2
b00000000000100010010001000110011010001000101010101100110011101111000100010011001101010101011101111001100110111011110111011111111 4
b00000000000000000000000000000000000000000000000000000000000000000000000000000000000000000000000000000000000000000000000000000000 ,
b0000 -
0"
0.
03
#20000
0%
#25000
1%
#30000
0%
0&
#35000
1%
#40000
0%
#45000
1%
#50000
0%
1&
#55000
1%
#60000
0%
#65000
1%
#70000
0%
0&
#75000
1%
#80000
0%
#85000
1%
#90000
0%
b00000000000100010010001000110011 )
1(
#95000
1%
b00000000000100010010001000110011 /
b00000000000000000000000000000000010001000101010101100110011101111000100010011001101010101011101111001100110111011110111011111111 4
b00000000000100010010001000110011000000000000000000000000000000000000000000000000000000000000000000000000000000000000000000000000 ,
b0001 -
#100000
0%
0(
#105000
1%
#110000
0%
b01 *
b01000100010101010110011001110111 )
1(
#115000
1%
b01000100010101010110011001110111 0
b00000000000000000000000000000000000000000000000000000000000000001000100010011001101010101011101111001100110111011110111011111111 4
b00000000000100010010001000110011010001000101010101100110011101110000000000000000000000000000000000000000000000000000000000000000 ,
b0011 -
#120000
0%
0(
#125000
1%
#130000
0%
1!
#135000
1%
1$
#140000
0%
0!
#145000
1%
0$
#150000
0%
1&
#155000
1%
b00000000000000000000000000000000 /
b00000000000100010010001000110011000000000000000000000000000000001000100010011001101010101011101111001100110111011110111011111111 4
b00000000000000000000000000000000010001000101010101100110011101110000000000000000000000000000000000000000000000000000000000000000 ,
b00000000000000000000000000000000 0
b00000000000100010010001000110011010001000101010101100110011101111000100010011001101010101011101111001100110111011110111011111111 4
b00000000000000000000000000000000000000000000000000000000000000000000000000000000000000000000000000000000000000000000000000000000 ,
b0000 -
#160000
0%
#165000
1%
#170000
0%
0&
#175000
1%
#180000
0%
#185000
1%
#190000
0%
b00 *
b00000000000100010010001000110011 )
1(
#195000
1%
b00000000000100010010001000110011 /
b00000000000000000000000000000000010001000101010101100110011101111000100010011001101010101011101111001100110111011110111011111111 4
b00000000000100010010001000110011000000000000000000000000000000000000000000000000000000000000000000000000000000000000000000000000 ,
b0001 -
#200000
0%
0(
#205000
1%
#210000
0%
b01 *
b01000100010101010110011001110111 )
1(
#215000
1%
b01000100010101010110011001110111 0
b00000000000000000000000000000000000000000000000000000000000000001000100010011001101010101011101111001100110111011110111011111111 4
b00000000000100010010001000110011010001000101010101100110011101110000000000000000000000000000000000000000000000000000000000000000 ,
b0011 -
#220000
0%
0(
#225000
1%
#230000
0%
b10 *
b10001000100110011010101010111011 )
1(
#235000
1%
b10001000100110011010101010111011 1
b00000000000000000000000000000000000000000000000000000000000000000000000000000000000000000000000011001100110111011110111011111111 4
b00000000000100010010001000110011010001000101010101100110011101111000100010011001101010101011101100000000000000000000000000000000 ,
b0111 -
#240000
0%
0(
#245000
1%
#250000
0%
b11 *
b11001100110111011110111011111111 )
1(
#255000
1%
b11001100110111011110111011111111 2
b00000000000000000000000000000000000000000000000000000000000000000000000000000000000000000000000000000000000000000000000000000000 4
b00000000000100010010001000110011010001000101010101100110011101111000100010011001101010101011101111001100110111011110111011111111 ,
b1111 -
1"
13
#260000
0%
0(
#265000
1%
#270000
0%
1!
#275000
1%
1#
1.
#280000
0%
0!
#285000
1%
0#
#290000
0%
1&
#295000
1%
b00000000000000000000000000000000 /
b00000000000100010010001000110011000000000000000000000000000000000000000000000000000000000000000000000000000000000000000000000000 4
b00000000000000000000000000000000010001000101010101100110011101111000100010011001101010101011101111001100110111011110111011111111 ,
b00000000000000000000000000000000 0
b00000000000100010010001000110011010001000101010101100110011101110000000000000000000000000000000000000000000000000000000000000000 4
b00000000000000000000000000000000000000000000000000000000000000001000100010011001101010101011101111001100110111011110111011111111 ,
b00000000000000000000000000000000 1
b00000000000100010010001000110011010001000101010101100110011101111000100010011001101010101011101100000000000000000000000000000000 4
b00000000000000000000000000000000000000000000000000000000000000000000000000000000000000000000000011001100110111011110111011111111 ,
b00000000000000000000000000000000 2
b00000000000100010010001000110011010001000101010101100110011101111000100010011001101010101011101111001100110111011110111011111111 4
b00000000000000000000000000000000000000000000000000000000000000000000000000000000000000000000000000000000000000000000000000000000 ,
b0000 -
0"
0.
03
#300000
0%
#305000
1%
#310000
0%
0&
#315000
1%
#320000
0%
#325000
1%
#330000
0%
b00 *
b00000000000100010010001000110011 )
1(
#335000
1%
b00000000000100010010001000110011 /
b00000000000000000000000000000000010001000101010101100110011101111000100010011001101010101011101111001100110111011110111011111111 4
b00000000000100010010001000110011000000000000000000000000000000000000000000000000000000000000000000000000000000000000000000000000 ,
b0001 -
#340000
0%
0(
#345000
1%
#350000
0%
b01 *
b01000100010101010110011001110111 )
1(
#355000
1%
b01000100010101010110011001110111 0
b00000000000000000000000000000000000000000000000000000000000000001000100010011001101010101011101111001100110111011110111011111111 4
b00000000000100010010001000110011010001000101010101100110011101110000000000000000000000000000000000000000000000000000000000000000 ,
b0011 -
#360000
0%
0(
#365000
1%
#370000
0%
b10 *
b10001000100110011010101010111011 )
1(
#375000
1%
b10001000100110011010101010111011 1
b00000000000000000000000000000000000000000000000000000000000000000000000000000000000000000000000011001100110111011110111011111111 4
b00000000000100010010001000110011010001000101010101100110011101111000100010011001101010101011101100000000000000000000000000000000 ,
b0111 -
#380000
0%
0(
#385000
1%
#390000
0%
b11 *
b11001100110111011110111011111110 )
1(
#395000
1%
b11001100110111011110111011111110 2
b00000000000000000000000000000000000000000000000000000000000000000000000000000000000000000000000000000000000000000000000000000001 4
b00000000000100010010001000110011010001000101010101100110011101111000100010011001101010101011101111001100110111011110111011111110 ,
b1111 -
1"
#400000
0%
0(
#405000
1%
#410000
0%
1!
#415000
1%
1#
#420000
0%
0!
#425000
1%
0#
#430000
0%
1&
#435000
1%
b00000000000000000000000000000000 /
b00000000000100010010001000110011000000000000000000000000000000000000000000000000000000000000000000000000000000000000000000000001 4
b00000000000000000000000000000000010001000101010101100110011101111000100010011001101010101011101111001100110111011110111011111110 ,
b00000000000000000000000000000000 0
b00000000000100010010001000110011010001000101010101100110011101110000000000000000000000000000000000000000000000000000000000000001 4
b00000000000000000000000000000000000000000000000000000000000000001000100010011001101010101011101111001100110111011110111011111110 ,
b00000000000000000000000000000000 1
b00000000000100010010001000110011010001000101010101100110011101111000100010011001101010101011101100000000000000000000000000000001 4
b00000000000000000000000000000000000000000000000000000000000000000000000000000000000000000000000011001100110111011110111011111110 ,
b00000000000000000000000000000000 2
b00000000000100010010001000110011010001000101010101100110011101111000100010011001101010101011101111001100110111011110111011111111 4
b00000000000000000000000000000000000000000000000000000000000000000000000000000000000000000000000000000000000000000000000000000000 ,
b0000 -
0"
#440000
0%
#445000
1%
#450000
0%
0&
#455000
1%
#460000
0%
#465000
1%
#470000
0%
b00 *
b00000000000100010010001000110011 )
1(
#475000
1%
b00000000000100010010001000110011 /
b00000000000000000000000000000000010001000101010101100110011101111000100010011001101010101011101111001100110111011110111011111111 4
b00000000000100010010001000110011000000000000000000000000000000000000000000000000000000000000000000000000000000000000000000000000 ,
b0001 -
#480000
0%
0(
#485000
1%
#490000
0%
b01 *
b01000100010101010110011001110111 )
1(
#495000
1%
b01000100010101010110011001110111 0
b00000000000000000000000000000000000000000000000000000000000000001000100010011001101010101011101111001100110111011110111011111111 4
b00000000000100010010001000110011010001000101010101100110011101110000000000000000000000000000000000000000000000000000000000000000 ,
b0011 -
#500000
0%
0(
#505000
1%
#510000
0%
b10 *
b10001000100110011010101010111011 )
1(
#515000
1%
b10001000100110011010101010111011 1
b00000000000000000000000000000000000000000000000000000000000000000000000000000000000000000000000011001100110111011110111011111111 4
b00000000000100010010001000110011010001000101010101100110011101111000100010011001101010101011101100000000000000000000000000000000 ,
b0111 -
#520000
0%
0(
#525000
1%
#530000
0%
b11 *
b11001100110111011110111011111111 )
1(
1!
#535000
1%
1$
#540000
0%
0(
0!
#545000
1%
0$
#550000
0%
1&
#555000
1%
b00000000000000000000000000000000 /
b00000000000100010010001000110011000000000000000000000000000000000000000000000000000000000000000011001100110111011110111011111111 4
b00000000000000000000000000000000010001000101010101100110011101111000100010011001101010101011101100000000000000000000000000000000 ,
b00000000000000000000000000000000 0
b00000000000100010010001000110011010001000101010101100110011101110000000000000000000000000000000011001100110111011110111011111111 4
b00000000000000000000000000000000000000000000000000000000000000001000100010011001101010101011101100000000000000000000000000000000 ,
b00000000000000000000000000000000 1
b00000000000100010010001000110011010001000101010101100110011101111000100010011001101010101011101111001100110111011110111011111111 4
b00000000000000000000000000000000000000000000000000000000000000000000000000000000000000000000000000000000000000000000000000000000 ,
b0000 -
#560000
0%
#565000
1%
#570000
0%
0&
#575000
1%
#580000
0%
#585000
1%
#590000
0%
b00 *
b00000000000100010010001000110011 )
1(
#595000
1%
b00000000000100010010001000110011 /
b00000000000000000000000000000000010001000101010101100110011101111000100010011001101010101011101111001100110111011110111011111111 4
b00000000000100010010001000110011000000000000000000000000000000000000000000000000000000000000000000000000000000000000000000000000 ,
b0001 -
#600000
0%
0(
#605000
1%
#610000
0%
b01 *
b01000100010101010110011001110111 )
1(
#615000
1%
b01000100010101010110011001110111 0
b00000000000000000000000000000000000000000000000000000000000000001000100010011001101010101011101111001100110111011110111011111111 4
b00000000000100010010001000110011010001000101010101100110011101110000000000000000000000000000000000000000000000000000000000000000 ,
b0011 -
#620000
0%
0(
#625000
1%
#630000
0%
b10 *
b10001000100110011010101010111011 )
1(
#635000
1%
b10001000100110011010101010111011 1
b00000000000000000000000000000000000000000000000000000000000000000000000000000000000000000000000011001100110111011110111011111111 4
b00000000000100010010001000110011010001000101010101100110011101111000100010011001101010101011101100000000000000000000000000000000 ,
b0111 -
#640000
0%
0(
#645000
1%
#650000
0%
b11 *
b11001100110111011110111011111111 )
1(
#655000
1%
b11001100110111011110111011111111 2
b00000000000000000000000000000000000000000000000000000000000000000000000000000000000000000000000000000000000000000000000000000000 4
b00000000000100010010001000110011010001000101010101100110011101111000100010011001101010101011101111001100110111011110111011111111 ,
b1111 -
1"
13
#660000
0%
0(
#665000
1%
#670000
0%
1!
#675000
1%
1#
1.
#680000
0%
0!
#685000
1%
0#
#690000
0%
1'
#695000
1%
b00000000000000000000000000000000 /
b00000000000100010010001000110011000000000000000000000000000000000000000000000000000000000000000000000000000000000000000000000000 4
b00000000000000000000000000000000010001000101010101100110011101111000100010011001101010101011101111001100110111011110111011111111 ,
b00000000000000000000000000000000 0
b00000000000100010010001000110011010001000101010101100110011101110000000000000000000000000000000000000000000000000000000000000000 4
b00000000000000000000000000000000000000000000000000000000000000001000100010011001101010101011101111001100110111011110111011111111 ,
b00000000000000000000000000000000 1
b00000000000100010010001000110011010001000101010101100110011101111000100010011001101010101011101100000000000000000000000000000000 4
b00000000000000000000000000000000000000000000000000000000000000000000000000000000000000000000000011001100110111011110111011111111 ,
b00000000000000000000000000000000 2
b00000000000100010010001000110011010001000101010101100110011101111000100010011001101010101011101111001100110111011110111011111111 4
b00000000000000000000000000000000000000000000000000000000000000000000000000000000000000000000000000000000000000000000000000000000 ,
b0000 -
0"
0.
03
#700000
0%
0'
