fsm-aribter/rtl/fsm_using_one_always.v
`timescale 1ns/1ps
module fsm_using_one_always(
clock,
reset,
req_0,
req_1,
gnt_0,
gnt_1
);
// inputs
input clock, reset, req_0, req_1;
wire clock, reset, req_0, req_1;
// outputs
output gnt_0, gnt_1;
reg gnt_0, gnt_1;
// internal constraints
parameter size = 3;
parameter IDLE = 3'b001, GNT0 = 3'b010, GNT1 = 3'b100;
// internal vars
reg [size-1:0] state; // seq logic
reg [size-1:0] next_state; // comb logic
reg req0_d, req1_d;
//logic
always @(posedge clock) 
begin : FSM
    if (reset) begin
        state <= IDLE;
        gnt_0 <= 1'b0;
        gnt_1 <= 1'b0;
        req0_d <= 1'b0;
        req1_d <= 1'b0;
    end
    else begin
        req0_d <= req_0;
        req1_d <= req_1;
        // default state unless set
        gnt_0 <= 1'b0;
        gnt_1 <= 1'b0;
        case(state) 
            IDLE : 
                if(req0_d) begin
                    state <= GNT0;
                    gnt_0 <= 1;
                end   
                else if (req1_d) begin
                    state <= GNT1;
                    gnt_1 <= 1;
                end
                else begin
                    state <= IDLE;
                end
            GNT0 :
                if (req_0) begin
                    state <= GNT0;
                    gnt_0 <= 1'b1; 
               end
                else begin
                    state <= IDLE;  
                    gnt_0 <= 1'b0;
                end
            GNT1:
                if (req_1) begin
                    state <= GNT1;
                    gnt_1 <= 1'b1;
                end
                else begin
                    state <= IDLE;
                    gnt_1 <= 1'b0;
                end
            default : state <= #1 IDLE; 
        endcase
    end
end
endmodule

fsm-aribter/sim/tb_fsm_one.sv
`timescale 1ns/1ps

module tb_fsm_using_one_always;
    // DUT inputs
    reg clock;
    reg reset;
    reg req_0;
    reg req_1;
    // DUT outputs
    wire gnt_0;
    wire gnt_1;
    
    // init DUT
    fsm_using_one_always dut(
        .clock(clock),
        .reset(reset),
        .req_0(req_0),
        .req_1(req_1),
        .gnt_0(gnt_0),
        .gnt_1(gnt_1)
    );

    clocking cb @(posedge clock);
        default input #1step;
        input gnt_0,gnt_1,req_0,req_1,reset;
    endclocking

    // MUTUAL EXLCUSION: Never grant both
    a_mutex : assert property (@(posedge clock) disable iff (cb.reset || $isunknown({cb.gnt_0,cb.gnt_1}))
        !(cb.gnt_0 && cb.gnt_1)
    ) else $fatal(1, "Arbiter Failure: Both grants high at t=%0t", $time);

    // False high check : if gnt_0 then we expect req_0
    false_high_gnt0 : assert property (@(posedge clock) disable iff (cb.reset || $isunknown({cb.gnt_0,cb.req_0}))
        cb.gnt_0 |-> $past(cb.req_0)
    ) else $fatal(1, "gnt_0 high while req_0 low at t=%0t", $time);

    // if gnt_1 we expect req_1
    false_high_gnt1 : assert property (@(posedge clock) disable iff(cb.reset || $isunknown({cb.gnt_1,cb.req_1}))
        cb.gnt_1 |-> $past(cb.req_1)
    ) else $fatal(1,"gnt_1 high while req_1 low at t=%0t", $time);

    a_no_tail0 : assert property (@(posedge clock)
        disable iff (reset || $isunknown({gnt_0, req_0}))
        !(gnt_0 && req_0)
    ) else $fatal(1, "Tail detected: gnt_0=1 while req_0=0 at t=%0t", $time);

    a_no_tail1 : assert property (@(posedge clock)
        disable iff (reset || $isunknown({gnt_1, req_1}))
        !(gnt_1 && req_1)
    ) else $fatal(1, "Tail detected: gnt_1=1 while req_1=0 at t=%0t", $time);
    
    task tb_expect;
        input [255:0] name;
        input actual;
        input expected;
    begin 
        if (actual !== expected) begin
            $display("Failure: %0s at t=%0t actual=%b expected=%b",name, $time, actual, expected);
            $finish;
        end
        else begin
            $display("Pass: %0s at t=%0t", name, $time);
        end
    end
    endtask
    
    initial begin
        clock = 0;
        forever #5 clock = ~clock;
    end
    
    // test stimuli
    initial begin
        $display(" === Begin Test Seq == ");
        // init signals
        reset = 0;
        req_0 = 0;
        req_1 = 0;
        
        // dump waveforms
        $dumpfile("fsm_one.vcd");
        $dumpvars(0, tb_fsm_using_one_always);
    
        // Hold reset for a few cycle
        @(negedge clock);
        reset = 1;
        @(negedge clock);
        @(negedge clock);
        reset = 0;
        @(negedge clock);
        
        // request 0 for 2 cycles
        req_0 = 1;
        @(posedge clock); #1;
        tb_expect("no immdiate grant", gnt_0, 1'b0);
        tb_expect("gnt_1 stays low when req_0 high", gnt_1, 1'b0);
        
        // hold for one cycle
        @(posedge clock); #1;   
        tb_expect("gnt_0 high after second cycle", gnt_0, 1'b1);
        @(negedge clock);
        req_0 = 1'b0;
        
        // after following pos edge gnt_0 should fall
        @(posedge clock); #1;
        tb_expect("gnt_0 deasserted immediatley", gnt_0, 1'b0);                
        
        @(posedge clock); #1;
        tb_expect("gnt_0 desserted one cycle adter req_0 low", gnt_0, 1'b0);        

        @(negedge clock);
        @(negedge clock);
        @(negedge clock);

        // test req/gnt 1
        reset = 1; 
        @(negedge clock);    
        @(negedge clock);
        reset = 0;
        @(negedge clock);
        // resquest 1
        req_1 = 1;
        @(posedge clock); #1;
        tb_expect("No immdiate grant",gnt_1, 1'b0);
        tb_expect("gnt_0 stays low when req_1 high",gnt_0, 1'b0);
        // hold for one cycle
        @(posedge clock); #1;
        tb_expect("gnt_1 high after one cycle", gnt_1, 1'b1);
        @(negedge clock);
        req_1 = 1'b0;
        @(posedge clock); #1;
        // after following positive edge we expect gnt_1 to fall
        tb_expect("gnt_1 low after one cycle", gnt_1, 1'b0);

        $display("=== Finish Test Seq === ");
        $finish;

    end
    
    // monitor on different signals
    initial begin
        $display("time   clk  rst  req0  req1 | gnt0  gnt1 | state");
        $monitor("%4t     %0b  %0b  %0b   %0b  | %0b   %0b |  %3b",$time, clock, reset, req_0, req_1, gnt_0, gnt_1, dut.state);
    end 

endmodule

fsm-aribter/build/fsm_one.vcd
$date
	Mon Feb 23 21:43:50 2026
$end

$version
	Synopsys VCS version W-2024.09
$end

$timescale
	1ps
$end

$comment Csum: 1 d1b0663a78553bb0 $end


$scope module tb_fsm_using_one_always $end
$var reg 1 ! req_0 $end
$var reg 1 " req_1 $end
$var wire 1 # gnt_0 $end
$var wire 1 $ gnt_1 $end
$var reg 1 % clock $end
$var reg 1 & reset $end

$scope task tb_expect $end
$var reg 256 ' name [255:0] $end
$var reg 1 ( actual $end
$var reg 1 ) expected $end
$upscope $end


$scope task _$$txp______assert_a_mutex $end
$upscope $end


$scope task _$$txp______assert_false_high_gnt0 $end
$upscope $end


$scope task _$$txp______assert_false_high_gnt1 $end
$upscope $end


$scope task _$$txp______assert_a_no_tail0 $end
$upscope $end


$scope task _$$txp______assert_a_no_tail1 $end
$upscope $end


$scope task _$$txp_fail_action_a_mutex $end
$upscope $end


$scope task _$$txp_fail_action_false_high_gnt0 $end
$upscope $end


$scope task _$$txp_fail_action_false_high_gnt1 $end
$upscope $end


$scope task _$$txp_fail_action_a_no_tail0 $end
$upscope $end


$scope task _$$txp_fail_action_a_no_tail1 $end
$upscope $end


$scope module dut $end
$var reg 3 * state [2:0] $end
$var wire 1 + clock $end
$var wire 1 , reset $end
$var wire 1 - req_0 $end
$var wire 1 . req_1 $end
$var reg 1 / gnt_0 $end
$var reg 1 0 gnt_1 $end
$var reg 3 1 next_state [2:0] $end
$var reg 1 2 req0_d $end
$var reg 1 3 req1_d $end

$scope begin FSM $end
$upscope $end

$upscope $end

$upscope $end

$enddefinitions $end

#0
$dumpvars
0%
x/
x0
0-
0.
0,
x#
x$
x2
x3
0!
0"
0&
x(
x)
bxxx 1
bxxx *
bxxxxxxxxxxxxxxxxxxxxxxxxxxxxxxxxxxxxxxxxxxxxxxxxxxxxxxxxxxxxxxxxxxxxxxxxxxxxxxxxxxxxxxxxxxxxxxxxxxxxxxxxxxxxxxxxxxxxxxxxxxxxxxxxxxxxxxxxxxxxxxxxxxxxxxxxxxxxxxxxxxxxxxxxxxxxxxxxxxxxxxxxxxxxxxxxxxxxxxxxxxxxxxxxxxxxxxxxxxxxxxxxxxxxxxxxxxxxxxxxxxxxxxxxxxxxxxxx '
0+
$end
#5000
1%
1+
02
03
0/
0#
00
0$
#6000
b001 *
#10000
0%
0+
1&
1,
#15000
1%
1+
#20000
0%
0+
#25000
1%
1+
#30000
0%
0+
0&
0,
#35000
1%
1+
#40000
0%
0+
1!
1-
#45000
1%
1+
12
#46000
b0000000000000000000000000000000000000000000000000000000000000000000000000000000000000000000000000000000000000000000000000110111001101111001000000110100101101101011011010110010001101001011000010111010001100101001000000110011101110010011000010110111001110100 '
0(
0)
b0000000001100111011011100111010001011111001100010010000001110011011101000110000101111001011100110010000001101100011011110111011100100000011101110110100001100101011011100010000001110010011001010111000101011111001100000010000001101000011010010110011101101000 '
#50000
0%
0+
#55000
1%
1+
1/
1#
b010 *
#56000
b0000000000000000000000000110011101101110011101000101111100110000001000000110100001101001011001110110100000100000011000010110011001110100011001010111001000100000011100110110010101100011011011110110111001100100001000000110001101111001011000110110110001100101 '
1(
1)
#60000
0%
0+
0!
0-
#65000
1%
1+
02
0/
0#
b001 *
#66000
b0000000000000000000000000000000001100111011011100111010001011111001100000010000001100100011001010110000101110011011100110110010101110010011101000110010101100100001000000110100101101101011011010110010101100100011010010110000101110100011011000110010101111001 '
0(
0)
#70000
0%
0+
#75000
1%
1+
#76000
b0111001101100101011100100111010001100101011001000010000001101111011011100110010100100000011000110111100101100011011011000110010100100000011000010110010001110100011001010111001000100000011100100110010101110001010111110011000000100000011011000110111101110111 '
#80000
0%
0+
#85000
1%
1+
#90000
0%
0+
#95000
1%
1+
#100000
0%
0+
1&
1,
#105000
1%
1+
#110000
0%
0+
#115000
1%
1+
#120000
0%
0+
0&
0,
#125000
1%
1+
#130000
0%
0+
1"
1.
#135000
1%
1+
13
#136000
b0000000000000000000000000000000000000000000000000000000000000000000000000000000000000000000000000000000000000000000000000100111001101111001000000110100101101101011011010110010001101001011000010111010001100101001000000110011101110010011000010110111001110100 '
b0000000001100111011011100111010001011111001100000010000001110011011101000110000101111001011100110010000001101100011011110111011100100000011101110110100001100101011011100010000001110010011001010111000101011111001100010010000001101000011010010110011101101000 '
#140000
0%
0+
#145000
1%
1+
10
1$
b100 *
#146000
b0000000000000000000000000000000000000000000000000110011101101110011101000101111100110001001000000110100001101001011001110110100000100000011000010110011001110100011001010111001000100000011011110110111001100101001000000110001101111001011000110110110001100101 '
1(
1)
#150000
0%
0+
0"
0.
#155000
1%
1+
03
00
0$
b001 *
#156000
b0000000000000000000000000000000000000000000000000000000001100111011011100111010001011111001100010010000001101100011011110111011100100000011000010110011001110100011001010111001000100000011011110110111001100101001000000110001101111001011000110110110001100101 '
0(
0)
